mtmaod/__init__.py
mtmaod/chart.py
mtmaod/dataframe.py
mtmaod/indicator.py
mtmaod/path.py
mtmaod/plot.py
mtmaod/spatial.py
mtmaod/products/__init__.py
mtmaod/products/_template.py
mtmaod/products/_utils.py
mtmaod/products/aeronet.py
mtmaod/products/modis.py
mtmaod/products/sonet.py
mtmaod/products/viirs.py
mtmaod/utils/netCDF4.py
mtmaod/utils/pyhdf.py
mtmaod-1.0.25.dist-info/licenses/LICENSE
mtmaod-1.0.25.dist-info/METADATA
mtmaod-1.0.25.dist-info/WHEEL
mtmaod-1.0.25.dist-info/top_level.txt
mtmaod-1.0.25.dist-info/RECORD
