Metadata-Version: 2.4
Name: mtmaod
Version: 1.0.25
Summary: imutum's packages for aerosol optical depth retrieval
License: MIT License
Classifier: Development Status :: 3 - Alpha
Classifier: Programming Language :: Python :: 3.8
Classifier: Intended Audience :: Developers
Classifier: License :: OSI Approved :: MIT License
Classifier: Operating System :: MacOS
Classifier: Operating System :: POSIX :: Linux
Classifier: Operating System :: Microsoft :: Windows
Requires-Python: >=3.8
License-File: LICENSE
Requires-Dist: matplotlib
Requires-Dist: numpy
Requires-Dist: pandas
Requires-Dist: mtmtool
Requires-Dist: scikit-learn
Requires-Dist: scipy>=1.10
Requires-Dist: shapely>=2.0.0
Requires-Dist: geopandas>=0.13.2
Dynamic: license-file
